curlipie/__init__.py
curlipie/compat.py
curlipie/curly.py
curlipie/pie.py
curlipie-0.8.3.dist-info/WHEEL
curlipie-0.8.3.dist-info/METADATA
curlipie-0.8.3.dist-info/RECORD
