Metadata-Version: 2.1
Name: curlipie
Version: 0.8.3
Summary: Library to convert cURL command line to HTTPie
Home-page: https://github.com/hongquan/CurliPie.git
License: MPL-2.0
Keywords: api,http,curl,httpie,cli,conversion
Author: Nguyễn Hồng Quân
Author-email: ng.hong.quan@gmail.com
Maintainer: Nguyễn Hồng Quân
Maintainer-email: ng.hong.quan@gmail.com
Requires-Python: >=3.6.1,<4.0.0
Classifier: Environment :: Web Environment
Classifier: Intended Audience :: Developers
Classifier: Intended Audience :: System Administrators
Classifier: License :: OSI Approved
Classifier: Programming Language :: Python :: 3
Classifier: Programming Language :: Python :: 3.7
Classifier: Programming Language :: Python :: 3.8
Classifier: Programming Language :: Python :: 3.9
Classifier: Topic :: Internet :: WWW/HTTP
Classifier: Topic :: Software Development :: Libraries :: Python Modules
Requires-Dist: Jinja2 (>=3.0.1,<4.0.0)
Requires-Dist: first (>=2.0.2,<3.0.0)
Requires-Dist: http-constants (>=0.4.0,<0.5.0)
Requires-Dist: kiss-headers (>=2.3.0,<3.0.0)
Requires-Dist: logbook (>=1.5.3,<2.0.0)
Requires-Dist: multidict (>=4.7.4,<5.0.0)
Requires-Dist: orjson (>=2.2.0,<3.0.0); python_version >= "3.7"
Requires-Dist: pydantic (>=1.8.2,<2.0.0)
Requires-Dist: python-rapidjson (>=0.9.1,<0.10.0); python_version ~= "3.6"
Requires-Dist: single-version (>=1.5.1,<2.0.0)
Requires-Dist: typed-argument-parser (>=1.7.0,<2.0.0)
Requires-Dist: yarl (>=1.4.2,<2.0.0)
Project-URL: Repository, https://github.com/hongquan/CurliPie.git
